ghoster/__init__.py
ghoster/browser.py
ghoster/motion.py
ghoster_py-1.0.3.dist-info/METADATA
ghoster_py-1.0.3.dist-info/WHEEL
ghoster_py-1.0.3.dist-info/top_level.txt
ghoster_py-1.0.3.dist-info/RECORD
