Metadata-Version: 2.4
Name: ghoster-py
Version: 1.0.3
Summary: A powerful stealth automation library for Playwright designed to mimic human behavior and bypass advanced bot detection systems.
Author-email: Hussain Al-Khatib <h2311065@gmail.com>
License-Expression: MIT
Classifier: Programming Language :: Python :: 3
Classifier: Operating System :: OS Independent
Requires-Python: >=3.8
Requires-Dist: playwright
Requires-Dist: playwright-stealth
